README.md
setup.py
certbot_cloudns/__init__.py
certbot_cloudns/plugin.py
certbot_plugin_cloudns.egg-info/PKG-INFO
certbot_plugin_cloudns.egg-info/SOURCES.txt
certbot_plugin_cloudns.egg-info/dependency_links.txt
certbot_plugin_cloudns.egg-info/entry_points.txt
certbot_plugin_cloudns.egg-info/requires.txt
certbot_plugin_cloudns.egg-info/top_level.txt